{
  "scriptId": "388",
  "url": "file:///C:/Studio/inspatial-core/packages/core/dev/util/src/abortable.ts",
  "functions": [
    {
      "functionName": "",
      "ranges": [{ "startOffset": 0, "endOffset": 8107, "count": 1 }],
      "isBlockCoverage": true
    },
    {
      "functionName": "abortable",
      "ranges": [{ "startOffset": 5598, "endOffset": 5762, "count": 0 }],
      "isBlockCoverage": false
    },
    {
      "functionName": "abortablePromise",
      "ranges": [{ "startOffset": 6339, "endOffset": 6718, "count": 0 }],
      "isBlockCoverage": false
    },
    {
      "functionName": "abortableAsyncIterable",
      "ranges": [{ "startOffset": 7352, "endOffset": 8106, "count": 0 }],
      "isBlockCoverage": false
    }
  ]
}
